simple_editor/__init__.py
simple_editor/changefont.py
simple_editor/editor.png
simple_editor/help.txt
simple_editor/hen.egg
simple_editor/moon.egg
simple_editor-0.4.5.dist-info/LICENSE
simple_editor-0.4.5.dist-info/METADATA
simple_editor-0.4.5.dist-info/WHEEL
simple_editor-0.4.5.dist-info/top_level.txt
simple_editor-0.4.5.dist-info/RECORD
