Metadata-Version: 2.1
Name: simple-editor
Version: 0.4.5
Summary: GUI-editor for Python development.
Home-page: https://github.com/SamuelKos/simple-editor
Author: SamuelKos
Author-email: author@example.com
Project-URL: Bug Tracker, https://github.com/SamuelKos/simple-editor/issues
Classifier: Programming Language :: Python :: 3.9
Classifier: License :: OSI Approved :: GNU General Public License v3 (GPLv3)
Classifier: Operating System :: POSIX :: Linux
Classifier: Intended Audience :: Developers
Classifier: Topic :: Software Development
Classifier: Topic :: Text Editors
Requires-Python: >=3.6
License-File: LICENSE
